MANIFEST.in
README.rst
setup.py
test/test_apps.py
wsgilite/__init__.py
wsgilite/autoreloader.py
wsgilite/wsgilite.py
wsgilite.egg-info/PKG-INFO
wsgilite.egg-info/SOURCES.txt
wsgilite.egg-info/dependency_links.txt
wsgilite.egg-info/entry_points.txt
wsgilite.egg-info/requires.txt
wsgilite.egg-info/top_level.txt
wsgilite/apps/__init__.py
wsgilite/apps/dynamic.py
wsgilite/apps/echo.py
wsgilite/apps/static.py
wsgilite/config/__init__.py
wsgilite/config/db.py
wsgilite/extras/__init__.py
wsgilite/extras/fancyindex.py
wsgilite/extras/restructured.py
wsgilite/extras/templates/index.rst
wsgilite/extras/templates/tablelist.rst
wsgilite/framework/__init__.py
wsgilite/framework/cn.py
wsgilite/framework/method.py
wsgilite/framework/selector.py