Metadata-Version: 1.0
Name: wsgilite
Version: 0.1.0
Summary: a grab-bag of web app utilities for developer convenience
Home-page: https://github.com/danbornside/wsgilite
Author: dan bornside
Author-email: dan.bornside@gmail.com
License: UNKNOWN
Platform: UNKNOWN
